coreli/Collatz_maps.py
coreli/Collatz_tilings.py
coreli/__init__.py
coreli/padic_integers.py
coreli/parity_vectors.py
coreli/utils.py
coreli/tinytiles/__init__.py
coreli/tinytiles/interactive.py
coreli/tinytiles/model.py
coreli/tinytiles/svg_view.py
coreli-0.0.5.dist-info/LICENSE
coreli-0.0.5.dist-info/METADATA
coreli-0.0.5.dist-info/WHEEL
coreli-0.0.5.dist-info/top_level.txt
coreli-0.0.5.dist-info/RECORD
