Metadata-Version: 2.1
Name: coreli
Version: 0.0.5
Summary: The Collatz Research Library provides tools for experimenting and testing hypothesises related to the Collatz Process.
Home-page: https://github.com/tcosmo/coreli
Author: Tristan Stérin
Author-email: tristan.sterin@mu.ie
Classifier: Programming Language :: Python :: 3
Classifier: License :: OSI Approved :: MIT License
Classifier: Operating System :: OS Independent
Requires-Python: >=3.6
License-File: LICENSE
Requires-Dist: sympy (==1.11.1)
Requires-Dist: drawsvg (==1.8.3)
Requires-Dist: ipywidgets (==8.0.2)
